{
  "text": {
    "hi": 18,
    "hello": 16,
    "hey": 17,
    "there": 48,
    "my": 30,
    "name": 31,
    "is": 22,
    "john": 24,
    "doe": 11,
    "it": 23,
    "s": 44,
    "maria": 27,
    "check": 8,
    "in": 20,
    "on": 35,
    "__number__": 0,
    "i": 19,
    "arrive": 3,
    "out": 37,
    "leaving": 25,
    "guests": 15,
    "only": 36,
    "me": 28,
    "we": 50,
    "are": 2,
    "single": 45,
    "room": 43,
    "double": 12,
    "suite": 47,
    "please": 40,
    "yes": 52,
    "breakfast": 5,
    "no": 33,
    "want": 49,
    "included": 21,
    "credit": 10,
    "card": 7,
    "ll": 26,
    "pay": 38,
    "with": 51,
    "paypal": 39,
    "refundable": 42,
    "nonrefundable": 34,
    "flexible": 13,
    "rate": 41,
    "confirm": 9,
    "go": 14,
    "ahead": 1,
    "book": 4,
    "stop": 46,
    "cancel": 6,
    "never": 32,
    "mind": 29
  },
  "intent": {
    "greet": 1,
    "provide_name": 6,
    "provide_checkin": 3,
    "provide_checkout": 4,
    "provide_guests": 5,
    "provide_room_type": 9,
    "provide_breakfast": 2,
    "provide_payment": 7,
    "provide_refund": 8,
    "confirm_booking": 0,
    "stop": 10
  },
  "response": null,
  "action_name": {
    "action_listen": 6,
    "action_restart": 7,
    "action_session_start": 9,
    "action_default_fallback": 4,
    "action_deactivate_loop": 1,
    "action_revert_fallback_events": 8,
    "action_default_ask_affirmation": 2,
    "action_default_ask_rephrase": 3,
    "action_two_stage_fallback": 10,
    "action_unlikely_intent": 11,
    "action_back": 0,
    "action_extract_slots": 5,
    "booking_form": 12,
    "utter_goodbye": 13,
    "utter_summary": 14
  },
  "action_text": null,
  "intent_response_key": null
}